README
setup.py
pagosonline/__init__.py
pagosonline/config.py
pagosonline/models.py
pagosonline/processor.py
pagosonline/urls.py
pagosonline/version.py
pagosonline/views.py
pagosonline.egg-info/PKG-INFO
pagosonline.egg-info/SOURCES.txt
pagosonline.egg-info/dependency_links.txt
pagosonline.egg-info/top_level.txt