Metadata-Version: 1.0
Name: pagosonline
Version: 0.5.2
Summary: Satchmo gateway for the Colombian pagosonline service
Home-page: http://github.com/jeasas/pagosonline
Author: Mauricio Mercado
Author-email: maumercado@gmail.com
License: BSD
Keywords: satchmo pagosonline
Platform: UNKNOWN
Classifier: Development Status :: 4 - Beta
Classifier: Intended Audience :: Developers
Classifier: License :: OSI Approved :: BSD License
Classifier: Operating System :: OS Independent
Classifier: Programming Language :: Python
